<annotation>
  <folder></folder>
  <filename>Screenshot (690).png</filename>
  <source>
    <database>Unknown</database>
    <annotation>Unknown</annotation>
    <image>Unknown</image>
  </source>
  <size>
    <width>1920</width>
    <height>1080</height>
    <depth></depth>
  </size>
  <segmented>0</segmented>
  <object>
    <name>Pedestrian</name>
    <truncated>0</truncated>
    <occluded>0</occluded>
    <difficult>0</difficult>
    <bndbox>
      <xmin>151.25</xmin>
      <ymin>296.5</ymin>
      <xmax>235.42</xmax>
      <ymax>416.98</ymax>
    </bndbox>
    <attributes>
      <attribute>
        <name>rotation</name>
        <value>0.0</value>
      </attribute>
    </attributes>
  </object>
  <object>
    <name>Pedestrian</name>
    <truncated>0</truncated>
    <occluded>0</occluded>
    <difficult>0</difficult>
    <bndbox>
      <xmin>249.67</xmin>
      <ymin>345.76</ymin>
      <xmax>336.43</xmax>
      <ymax>431.5</ymax>
    </bndbox>
    <attributes>
      <attribute>
        <name>rotation</name>
        <value>0.0</value>
      </attribute>
    </attributes>
  </object>
  <object>
    <name>Car</name>
    <truncated>0</truncated>
    <occluded>0</occluded>
    <difficult>0</difficult>
    <bndbox>
      <xmin>1286.94</xmin>
      <ymin>374.2</ymin>
      <xmax>1459.6</xmax>
      <ymax>564.6</ymax>
    </bndbox>
    <attributes>
      <attribute>
        <name>rotation</name>
        <value>0.0</value>
      </attribute>
    </attributes>
  </object>
  <object>
    <name>Car</name>
    <truncated>0</truncated>
    <occluded>0</occluded>
    <difficult>0</difficult>
    <bndbox>
      <xmin>431.34</xmin>
      <ymin>407.3</ymin>
      <xmax>1289.2</xmax>
      <ymax>780.7</ymax>
    </bndbox>
    <attributes>
      <attribute>
        <name>rotation</name>
        <value>0.0</value>
      </attribute>
    </attributes>
  </object>
  <object>
    <name>Car</name>
    <truncated>0</truncated>
    <occluded>0</occluded>
    <difficult>0</difficult>
    <bndbox>
      <xmin>1467.31</xmin>
      <ymin>326.1</ymin>
      <xmax>1913.2</xmax>
      <ymax>684.59</ymax>
    </bndbox>
    <attributes>
      <attribute>
        <name>rotation</name>
        <value>0.0</value>
      </attribute>
    </attributes>
  </object>
  <object>
    <name>Car</name>
    <truncated>0</truncated>
    <occluded>0</occluded>
    <difficult>0</difficult>
    <bndbox>
      <xmin>11.4</xmin>
      <ymin>393.67</ymin>
      <xmax>423.19</xmax>
      <ymax>710.94</ymax>
    </bndbox>
    <attributes>
      <attribute>
        <name>rotation</name>
        <value>0.0</value>
      </attribute>
    </attributes>
  </object>
</annotation>
